[{"items":[{"id":"m2","name":"Margherita Pizza","price":"12.99","description":"A classic pizza with fresh mozzarella, tomatoes, and basil on a thin and crispy crust.","image":"images/margherita-pizza.jpg","quantity":2}],"customer":{"name":"asda","email":"asdas@dasfns","street":"dakndl","postal-code":"nfofnsd","city":"fjo"},"id":"848.7216181252551"},{"items":[{"id":"m2","name":"Margherita Pizza","price":"12.99","description":"A classic pizza with fresh mozzarella, tomatoes, and basil on a thin and crispy crust.","image":"images/margherita-pizza.jpg","quantity":2}],"customer":{"name":"asda","email":"asdas@dasfns","street":"dakndl","postal-code":"nfofnsd","city":"fjo"},"id":"587.3360649561458"},{"items":[{"id":"m2","name":"Margherita Pizza","price":"12.99","description":"A classic pizza with fresh mozzarella, tomatoes, and basil on a thin and crispy crust.","image":"images/margherita-pizza.jpg","quantity":2}],"customer":{"name":"asda","email":"asdas@dasfns","street":"dakndl","postal-code":"nfofnsd","city":"fjo"},"id":"728.1540583172988"},{"items":[{"id":"m5","name":"Veggie Burger","price":"9.99","description":"A juicy veggie patty served on a whole grain bun with lettuce, tomato, and a tangy sauce.","image":"images/veggie-burger.jpg","quantity":2}],"customer":{"name":"sdDASDF","email":"afadsf@wefs","street":"asdfs","postal-code":"fdsgf","city":"fdsfg"},"id":"297.7430075608332"},{"items":[{"id":"m1","name":"Mac & Cheese","price":"8.99","description":"Creamy cheddar cheese mixed with perfectly cooked macaroni, topped with crispy breadcrumbs. A classic comfort food.","image":"images/mac-and-cheese.jpg","quantity":1},{"id":"m4","name":"Spaghetti Carbonara","price":"10.99","description":"Al dente spaghetti with a creamy sauce made from egg yolk, pecorino cheese, pancetta, and pepper.","image":"images/spaghetti-carbonara.jpg","quantity":1},{"id":"m8","name":"Sushi Roll Platter","price":"15.99","description":"An assortment of fresh sushi rolls including California, Spicy Tuna, and Eel Avocado.","image":"images/sushi-roll-platter.jpg","quantity":2}],"customer":{"name":"asdfmkdnbk","email":"nk@fdsfs","street":"zkjdfnn","postal-code":"knfks","city":"dzvfdkjs"},"id":"730.9388282266875"},{"items":[{"id":"m2","name":"Margherita Pizza","price":"12.99","description":"A classic pizza with fresh mozzarella, tomatoes, and basil on a thin and crispy crust.","image":"images/margherita-pizza.jpg","quantity":4}],"customer":{"name":"fdsjn","email":"jkdsbafgjksd@fjsdgnj","street":"sdklgjioj8n","postal-code":"ngdsg","city":"suidgnds"},"id":"788.6388594095848"},{"items":[{"id":"m2","name":"Margherita Pizza","price":"12.99","description":"A classic pizza with fresh mozzarella, tomatoes, and basil on a thin and crispy crust.","image":"images/margherita-pizza.jpg","quantity":1},{"id":"m1","name":"Mac & Cheese","price":"8.99","description":"Creamy cheddar cheese mixed with perfectly cooked macaroni, topped with crispy breadcrumbs. A classic comfort food.","image":"images/mac-and-cheese.jpg","quantity":2}],"customer":{"name":"sdsafj","email":"fjsadnjfkg@FDSAF","street":"dsnjkgnksj","postal-code":"sdjkgnkj","city":"nfjkn"},"id":"911.4965925348073"},{"items":[{"id":"m2","name":"Margherita Pizza","price":"12.99","description":"A classic pizza with fresh mozzarella, tomatoes, and basil on a thin and crispy crust.","image":"images/margherita-pizza.jpg","quantity":4}],"customer":{"name":"safnjk","email":"jskdbgjk@fjsdnbjf","street":"jdfnsjkn","postal-code":"njksdgn","city":"bfnk"},"id":"419.7194929025139"}]